{"name":"build-javascript","namedChunkGroups":{"app":{"name":"app","assets":[{"name":"webpack-runtime-05fd61ba2c8bc2265380.js","size":3571},{"name":"framework-8b4a5b33a8394b96a326.js","size":140775},{"name":"app-0a5aa6781a58df0bbefc.js","size":61306}],"filteredAssets":0,"assetsSize":205652,"filteredAuxiliaryAssets":3,"auxiliaryAssetsSize":588275},"component---src-pages-404-js":{"name":"component---src-pages-404-js","assets":[{"name":"component---src-pages-404-js-d040ecf25e66d0e21f95.js","size":776}],"filteredAssets":0,"assetsSize":776,"filteredAuxiliaryAssets":1,"auxiliaryAssetsSize":1745},"component---src-pages-index-js":{"name":"component---src-pages-index-js","assets":[{"name":"component---src-pages-index-js-12196868510ccdd5a237.js","size":3808}],"filteredAssets":0,"assetsSize":3808,"filteredAuxiliaryAssets":1,"auxiliaryAssetsSize":7333}},"assetsByChunkName":{"app":["webpack-runtime-05fd61ba2c8bc2265380.js","framework-8b4a5b33a8394b96a326.js","app-0a5aa6781a58df0bbefc.js"],"component---src-pages-404-js":["component---src-pages-404-js-d040ecf25e66d0e21f95.js"],"component---src-pages-index-js":["component---src-pages-index-js-12196868510ccdd5a237.js"]},"childAssetsByChunkName":{}}